azure_devops_keyring/__init__.py
azure_devops_keyring/plugin.py
azure_devops_keyring/support.py
azure_devops_keyring/plugins/netcore/CredentialProvider.Microsoft/CredentialProvider.Microsoft.deps.json
azure_devops_keyring/plugins/netcore/CredentialProvider.Microsoft/CredentialProvider.Microsoft.dll
azure_devops_keyring/plugins/netcore/CredentialProvider.Microsoft/CredentialProvider.Microsoft.pdb
azure_devops_keyring/plugins/netcore/CredentialProvider.Microsoft/CredentialProvider.Microsoft.runtimeconfig.json
azure_devops_keyring/plugins/netcore/CredentialProvider.Microsoft/Microsoft.IdentityModel.Clients.ActiveDirectory.Platform.dll
azure_devops_keyring/plugins/netcore/CredentialProvider.Microsoft/Microsoft.IdentityModel.Clients.ActiveDirectory.dll
azure_devops_keyring/plugins/netcore/CredentialProvider.Microsoft/Newtonsoft.Json.dll
azure_devops_keyring/plugins/netcore/CredentialProvider.Microsoft/NuGet.Common.dll
azure_devops_keyring/plugins/netcore/CredentialProvider.Microsoft/NuGet.Configuration.dll
azure_devops_keyring/plugins/netcore/CredentialProvider.Microsoft/NuGet.Frameworks.dll
azure_devops_keyring/plugins/netcore/CredentialProvider.Microsoft/NuGet.Packaging.Core.dll
azure_devops_keyring/plugins/netcore/CredentialProvider.Microsoft/NuGet.Packaging.dll
azure_devops_keyring/plugins/netcore/CredentialProvider.Microsoft/NuGet.Protocol.dll
azure_devops_keyring/plugins/netcore/CredentialProvider.Microsoft/NuGet.Versioning.dll
azure_devops_keyring/plugins/netcore/CredentialProvider.Microsoft/PowerArgs.dll
azure_devops_keyring/plugins/netcore/CredentialProvider.Microsoft/runtimes/unix/lib/netstandard1.3/System.Security.Cryptography.ProtectedData.dll
azure_devops_keyring/plugins/netcore/CredentialProvider.Microsoft/runtimes/win/lib/netstandard1.3/System.Security.Cryptography.ProtectedData.dll
azure_devops_keyring/plugins/netfx/CredentialProvider.Microsoft/CredentialProvider.Microsoft.exe
azure_devops_keyring-0.3.dist-info/LICENSE
azure_devops_keyring-0.3.dist-info/METADATA
azure_devops_keyring-0.3.dist-info/WHEEL
azure_devops_keyring-0.3.dist-info/entry_points.txt
azure_devops_keyring-0.3.dist-info/top_level.txt
azure_devops_keyring-0.3.dist-info/RECORD
