Metadata-Version: 2.1
Name: azure-devops-keyring
Version: 0.3
Summary: "(Deprecated) Automatically retrieve passwords for Azure DevOps."
Home-page: https://github.com/Microsoft/azure-devops-keyring
Author: Microsoft Corporation
Author-email: python@microsoft.com
License: UNKNOWN
Platform: UNKNOWN
Classifier: Development Status :: 7 - Inactive
Classifier: Intended Audience :: Developers
Classifier: License :: OSI Approved :: MIT License
Classifier: Programming Language :: Python :: 2.7
Classifier: Programming Language :: Python :: 3.5
Classifier: Programming Language :: Python :: 3.6
Classifier: Programming Language :: Python :: 3.7
Requires-Python: >=2.7,!=3.0.*,!=3.1.*,!=3.2.*,!=3.3.*,!=3.4.*
Requires-Dist: keyring
Requires-Dist: dotnetcore2 ; sys_platform != "win32"
